numeta/__init__.py
numeta/array_shape.py
numeta/builder_helper.py
numeta/capi_interface.py
numeta/compiler.py
numeta/datatype.py
numeta/external_library.py
numeta/jit.py
numeta/numeta_function.py
numeta/registry.py
numeta/settings.py
numeta/signature.py
numeta/types_hint.py
numeta/external_modules/__init__.py
numeta/external_modules/iso_c_binding.py
numeta/external_modules/omp.py
numeta/syntax/__init__.py
numeta/syntax/derived_type.py
numeta/syntax/fortran_type.py
numeta/syntax/module.py
numeta/syntax/scope.py
numeta/syntax/settings.py
numeta/syntax/subroutine.py
numeta/syntax/tools.py
numeta/syntax/variable.py
numeta/syntax/expressions/__init__.py
numeta/syntax/expressions/binary_operation_node.py
numeta/syntax/expressions/expression_node.py
numeta/syntax/expressions/function.py
numeta/syntax/expressions/getattr.py
numeta/syntax/expressions/getitem.py
numeta/syntax/expressions/intrinsic_functions.py
numeta/syntax/expressions/literal_node.py
numeta/syntax/expressions/various.py
numeta/syntax/nodes/__init__.py
numeta/syntax/nodes/base_node.py
numeta/syntax/nodes/named_entity.py
numeta/syntax/statements/__init__.py
numeta/syntax/statements/call.py
numeta/syntax/statements/derived_type_declaration.py
numeta/syntax/statements/module_declaration.py
numeta/syntax/statements/statement.py
numeta/syntax/statements/subroutine_declaration.py
numeta/syntax/statements/tools.py
numeta/syntax/statements/variable_declaration.py
numeta/syntax/statements/various.py
numeta/wrappers/__init__.py
numeta/wrappers/cases.py
numeta/wrappers/cast.py
numeta/wrappers/cond.py
numeta/wrappers/constant.py
numeta/wrappers/declare_global_constant.py
numeta/wrappers/empty.py
numeta/wrappers/external_library.py
numeta/wrappers/numpy_mem.py
numeta/wrappers/prange.py
numeta/wrappers/range.py
numeta/wrappers/reshape.py
numeta/wrappers/scalar.py
numeta/wrappers/zeros.py
numeta-0.3.3.dist-info/licenses/LICENSE
numeta-0.3.3.dist-info/METADATA
numeta-0.3.3.dist-info/WHEEL
numeta-0.3.3.dist-info/top_level.txt
numeta-0.3.3.dist-info/RECORD
