Metadata-Version: 2.4
Name: numeta
Version: 0.3.3
Summary: Numeta is a small transpiler for Python with a metaprogramming focus.
Author-email: Andrea Bianchi <andrea_bianchi@outlook.com>
License: MIT
Requires-Python: >=3.12
License-File: LICENSE
Requires-Dist: numpy
Dynamic: license-file
